Proyecto1 (copy)/Paralelo_SerialFinal/probador.v
module probador(
    output reg [7:0] data_in,
    output reg clk_4f, clk_32f, valid_in, reset,
    input data_outCond, data_outSynth);

    //Inicializacion de relojes
    initial begin
        clk_4f <= 0;
        clk_32f <= 1;
    end
    always begin
        #32 clk_4f <= ~clk_4f;
    end
    always begin
        #4 clk_32f <= ~clk_32f;
    end
    
    initial begin
        $dumpfile("verificacion.vcd"); /*En este archivo se guardan todos los valores de la simulación*/
        $dumpvars;

        data_in <= 0;
        valid_in <= 0;
        reset <= 0;

        @(posedge clk_4f)
        reset <= 1;

        @(posedge clk_4f)
        data_in <= 'h9D;
    
        @(posedge clk_4f)
        data_in <= 'hFF;
        valid_in <= 1;

        @(posedge clk_4f)
        data_in <= 'hEE;
        
        @(posedge clk_4f)
        data_in <= 'hAF;
        valid_in <= 0;

        #100 $finish;
    end
endmodule

Proyecto1 (copy)/Paralelo_SerialFinal/Paralelo_SerialSynth.v
/* Generated by Yosys 0.9 (git sha1 1979e0b) */

(* top =  1  *)
(* src = "Paralelo_SerialSynth.v:1" *)
module Paralelo_SerialSynth(data_in, clk_4f, clk_32f, valid_in, reset, data_out);
  (* src = "Paralelo_SerialSynth.v:25" *)
  wire [7:0] _000_;
  wire _001_;
  wire _002_;
  wire _003_;
  wire _004_;
  wire _005_;
  wire _006_;
  wire _007_;
  wire _008_;
  wire _009_;
  wire _010_;
  wire _011_;
  wire _012_;
  wire _013_;
  wire _014_;
  wire _015_;
  wire _016_;
  wire _017_;
  wire _018_;
  wire _019_;
  wire _020_;
  wire _021_;
  wire _022_;
  wire _023_;
  wire _024_;
  wire _025_;
  wire _026_;
  wire _027_;
  wire _028_;
  wire _029_;
  wire _030_;
  wire _031_;
  wire _032_;
  wire _033_;
  wire _034_;
  wire _035_;
  wire _036_;
  wire _037_;
  wire _038_;
  wire _039_;
  wire _040_;
  wire _041_;
  wire _042_;
  wire _043_;
  wire _044_;
  wire _045_;
  wire _046_;
  wire _047_;
  wire _048_;
  wire _049_;
  wire _050_;
  wire _051_;
  wire _052_;
  wire _053_;
  wire _054_;
  wire _055_;
  wire _056_;
  wire _057_;
  wire _058_;
  wire _059_;
  wire _060_;
  wire _061_;
  wire _062_;
  wire _063_;
  wire _064_;
  wire _065_;
  (* src = "Paralelo_SerialSynth.v:3" *)
  input clk_32f;
  (* src = "Paralelo_SerialSynth.v:3" *)
  input clk_4f;
  (* src = "Paralelo_SerialSynth.v:6" *)
  wire [7:0] contador;
  (* src = "Paralelo_SerialSynth.v:2" *)
  input [7:0] data_in;
  (* src = "Paralelo_SerialSynth.v:4" *)
  output data_out;
  (* src = "Paralelo_SerialSynth.v:3" *)
  input reset;
  (* src = "Paralelo_SerialSynth.v:3" *)
  input valid_in;
  NOT _066_ (
    .A(contador[2]),
    .Y(_002_)
  );
  NOT _067_ (
    .A(contador[3]),
    .Y(_003_)
  );
  NOT _068_ (
    .A(contador[4]),
    .Y(_004_)
  );
  NOT _069_ (
    .A(contador[5]),
    .Y(_005_)
  );
  NOT _070_ (
    .A(contador[6]),
    .Y(_006_)
  );
  NOT _071_ (
    .A(contador[7]),
    .Y(_007_)
  );
  NOT _072_ (
    .A(reset),
    .Y(_008_)
  );
  NOT _073_ (
    .A(valid_in),
    .Y(_009_)
  );
  NOT _074_ (
    .A(contador[1]),
    .Y(_010_)
  );
  NOT _075_ (
    .A(contador[0]),
    .Y(_011_)
  );
  NAND _076_ (
    .A(reset),
    .B(contador[0]),
    .Y(_000_[0])
  );
  NOR _077_ (
    .A(contador[1]),
    .B(contador[0]),
    .Y(_012_)
  );
  NAND _078_ (
    .A(contador[1]),
    .B(contador[0]),
    .Y(_013_)
  );
  NAND _079_ (
    .A(reset),
    .B(_013_),
    .Y(_014_)
  );
  NOR _080_ (
    .A(_012_),
    .B(_014_),
    .Y(_015_)
  );
  NOT _081_ (
    .A(_015_),
    .Y(_000_[1])
  );
  NAND _082_ (
    .A(_002_),
    .B(_010_),
    .Y(_016_)
  );
  NOR _083_ (
    .A(contador[0]),
    .B(_016_),
    .Y(_017_)
  );
  NOT _084_ (
    .A(_017_),
    .Y(_018_)
  );
  NOR _085_ (
    .A(_002_),
    .B(_012_),
    .Y(_019_)
  );
  NOR _086_ (
    .A(_008_),
    .B(_019_),
    .Y(_020_)
  );
  NAND _087_ (
    .A(_018_),
    .B(_020_),
    .Y(_000_[2])
  );
  NOR _088_ (
    .A(contador[3]),
    .B(_018_),
    .Y(_021_)
  );
  NAND _089_ (
    .A(_003_),
    .B(_017_),
    .Y(_022_)
  );
  NOR _090_ (
    .A(_003_),
    .B(_017_),
    .Y(_023_)
  );
  NOR _091_ (
    .A(_021_),
    .B(_023_),
    .Y(_024_)
  );
  NOR _092_ (
    .A(contador[4]),
    .B(_022_),
    .Y(_025_)
  );
  NOT _093_ (
    .A(_025_),
    .Y(_026_)
  );
  NOR _094_ (
    .A(contador[5]),
    .B(_026_),
    .Y(_027_)
  );
  NAND _095_ (
    .A(_005_),
    .B(_025_),
    .Y(_028_)
  );
  NOR _096_ (
    .A(contador[6]),
    .B(_028_),
    .Y(_029_)
  );
  NAND _097_ (
    .A(_007_),
    .B(_029_),
    .Y(_030_)
  );
  NAND _098_ (
    .A(contador[7]),
    .B(reset),
    .Y(_031_)
  );
  NAND _099_ (
    .A(reset),
    .B(_030_),
    .Y(_032_)
  );
  NOR _100_ (
    .A(_024_),
    .B(_032_),
    .Y(_000_[3])
  );
  NOR _101_ (
    .A(_004_),
    .B(_021_),
    .Y(_033_)
  );
  NOR _102_ (
    .A(_025_),
    .B(_033_),
    .Y(_034_)
  );
  NOR _103_ (
    .A(_032_),
    .B(_034_),
    .Y(_000_[4])
  );
  NOR _104_ (
    .A(_005_),
    .B(_025_),
    .Y(_035_)
  );
  NOR _105_ (
    .A(_027_),
    .B(_035_),
    .Y(_036_)
  );
  NOR _106_ (
    .A(_032_),
    .B(_036_),
    .Y(_000_[5])
  );
  NOR _107_ (
    .A(_006_),
    .B(_027_),
    .Y(_037_)
  );
  NOR _108_ (
    .A(_029_),
    .B(_037_),
    .Y(_038_)
  );
  NOR _109_ (
    .A(_032_),
    .B(_038_),
    .Y(_000_[6])
  );
  NOR _110_ (
    .A(_029_),
    .B(_031_),
    .Y(_000_[7])
  );
  NOR _111_ (
    .A(data_in[0]),
    .B(_016_),
    .Y(_039_)
  );
  NAND _112_ (
    .A(_002_),
    .B(contador[1]),
    .Y(_040_)
  );
  NOR _113_ (
    .A(data_in[2]),
    .B(_040_),
    .Y(_041_)
  );
  NOR _114_ (
    .A(_039_),
    .B(_041_),
    .Y(_042_)
  );
  NAND _115_ (
    .A(contador[2]),
    .B(contador[1]),
    .Y(_043_)
  );
  NOR _116_ (
    .A(data_in[6]),
    .B(_043_),
    .Y(_044_)
  );
  NAND _117_ (
    .A(contador[2]),
    .B(_010_),
    .Y(_045_)
  );
  NOR _118_ (
    .A(data_in[4]),
    .B(_045_),
    .Y(_046_)
  );
  NOR _119_ (
    .A(_044_),
    .B(_046_),
    .Y(_047_)
  );
  NAND _120_ (
    .A(_042_),
    .B(_047_),
    .Y(_048_)
  );
  NAND _121_ (
    .A(_011_),
    .B(_048_),
    .Y(_049_)
  );
  NOR _122_ (
    .A(data_in[3]),
    .B(_040_),
    .Y(_050_)
  );
  NOR _123_ (
    .A(data_in[7]),
    .B(_043_),
    .Y(_051_)
  );
  NOR _124_ (
    .A(data_in[5]),
    .B(_045_),
    .Y(_052_)
  );
  NOR _125_ (
    .A(_051_),
    .B(_052_),
    .Y(_053_)
  );
  NOR _126_ (
    .A(contador[0]),
    .B(_043_),
    .Y(_054_)
  );
  NOR _127_ (
    .A(contador[3]),
    .B(valid_in),
    .Y(_055_)
  );
  NAND _128_ (
    .A(_016_),
    .B(_055_),
    .Y(_056_)
  );
  NOR _129_ (
    .A(_054_),
    .B(_056_),
    .Y(_057_)
  );
  NOR _130_ (
    .A(data_in[1]),
    .B(_016_),
    .Y(_058_)
  );
  NOR _131_ (
    .A(_050_),
    .B(_058_),
    .Y(_059_)
  );
  NAND _132_ (
    .A(_053_),
    .B(_059_),
    .Y(_060_)
  );
  NAND _133_ (
    .A(contador[0]),
    .B(_060_),
    .Y(_061_)
  );
  NOT _134_ (
    .A(_061_),
    .Y(_062_)
  );
  NOR _135_ (
    .A(contador[3]),
    .B(_009_),
    .Y(_063_)
  );
  NAND _136_ (
    .A(_049_),
    .B(_063_),
    .Y(_064_)
  );
  NOR _137_ (
    .A(_062_),
    .B(_064_),
    .Y(_065_)
  );
  NOR _138_ (
    .A(_057_),
    .B(_065_),
    .Y(_001_)
  );
  NOR _139_ (
    .A(_008_),
    .B(_001_),
    .Y(data_out)
  );
  (* src = "Paralelo_SerialSynth.v:25" *)
  DFF _140_ (
    .C(clk_32f),
    .D(_000_[0]),
    .Q(contador[0])
  );
  (* src = "Paralelo_SerialSynth.v:25" *)
  DFF _141_ (
    .C(clk_32f),
    .D(_000_[1]),
    .Q(contador[1])
  );
  (* src = "Paralelo_SerialSynth.v:25" *)
  DFF _142_ (
    .C(clk_32f),
    .D(_000_[2]),
    .Q(contador[2])
  );
  (* src = "Paralelo_SerialSynth.v:25" *)
  DFF _143_ (
    .C(clk_32f),
    .D(_000_[3]),
    .Q(contador[3])
  );
  (* src = "Paralelo_SerialSynth.v:25" *)
  DFF _144_ (
    .C(clk_32f),
    .D(_000_[4]),
    .Q(contador[4])
  );
  (* src = "Paralelo_SerialSynth.v:25" *)
  DFF _145_ (
    .C(clk_32f),
    .D(_000_[5]),
    .Q(contador[5])
  );
  (* src = "Paralelo_SerialSynth.v:25" *)
  DFF _146_ (
    .C(clk_32f),
    .D(_000_[6]),
    .Q(contador[6])
  );
  (* src = "Paralelo_SerialSynth.v:25" *)
  DFF _147_ (
    .C(clk_32f),
    .D(_000_[7]),
    .Q(contador[7])
  );
endmodule

Proyecto1/Paralelo_SerialFinal/Paralelo_Serial.v
module Paralelo_Serial(
    input [7:0] data_in,
    input clk_4f, clk_32f, valid_in, reset,
    output reg data_out);

    reg [7:0] data2send, contador;

    always @ (*) begin
        data2send = 0;
        data_out = 0;
        if (reset == 0) begin
            data2send = 0;
            data_out = 0;
        end
        else if (valid_in == 0) begin
            data2send = 'hBC;
            data_out = data2send[contador];
        end
        else if (valid_in == 1) begin
            data2send = data_in;
            data_out = data2send[contador];
        end
    end

    always @(posedge clk_32f) begin
         if (reset == 0) begin
            contador <= 7;
        end
        else if (contador == 0) begin
            contador <= 7;
        end
        else begin
            contador <= contador - 1;
        end      
    end
endmodule

Proyecto1/Paralelo_SerialFinal/testbench.v
`include "Paralelo_Serial.v"
`include "Paralelo_SerialSynth.v"
`include "probador.v"
`include "cmos_cells.v"

module testbench();

wire [7:0] data_in;
wire clk_4f, clk_32f, valid_in, reset, data_outCond, data_outSynth;

Paralelo_Serial PSCond (/*AUTOINST*/
			// Outputs
			.data_out	(data_outCond),
			// Inputs
			.data_in	(data_in[7:0]),
			.clk_4f		(clk_4f),
			.clk_32f	(clk_32f),
			.valid_in	(valid_in),
			.reset		(reset));

Paralelo_SerialSynth PSSynth (/*AUTOINST*/
			      // Outputs
			      .data_out		(data_outSynth),
			      // Inputs
			      .clk_32f		(clk_32f),
			      .clk_4f		(clk_4f),
			      .data_in		(data_in[7:0]),
			      .reset		(reset),
			      .valid_in		(valid_in));

probador probador (/*AUTOINST*/
		   // Outputs
		   .data_in		(data_in[7:0]),
		   .clk_4f		(clk_4f),
		   .clk_32f		(clk_32f),
		   .valid_in		(valid_in),
		   .reset		(reset),
		   // Inputs
		   .data_outCond	(data_outCond),
		   .data_outSynth	(data_outSynth));

endmodule

Tarea5/cmos_cellsRetardos.v
module BUF(A, Y);
input A;
output Y;
assign #(1:2.4:3.5, 1:2.4:3.5) Y = A;
endmodule

module NOT(A, Y);
input A;
output Y;
assign #(0.7:2:3.3, 0.7:2:3.3) Y = ~A;
endmodule

module NAND(A, B, Y);
input A, B;
output Y;
assign #(1:2.4:3.5, 1:2.4:3.5) Y = ~(A & B);
endmodule

module NOR(A, B, Y);
input A, B;
output Y;
assign #(0.9:2.25:3.6, 0.9:2.25:3.6) Y = ~(A | B);
endmodule

module DFF(C, D, Q);
input C, D;
output reg Q;
always @(posedge C)
	Q <= D;
endmodule

module DFFSR(C, D, Q, S, R);
input C, D, S, R;
output reg Q;
always @(posedge C, posedge S, posedge R)
	if (S)
		Q <= 1'b1;
	else if (R)
		Q <= 1'b0;
	else
		Q <= D;
endmodule

Proyecto1 (copy)/Avance2y3/Paralelo_Serial/verificacion.vcd
$date
	Thu Oct 21 19:32:14 2021
$end
$version
	Icarus Verilog
$end
$timescale
	1s
$end
$scope module BUF $end
$var wire 1 ! A $end
$var wire 1 " Y $end
$upscope $end
$scope module DFFSR $end
$var wire 1 # C $end
$var wire 1 $ D $end
$var wire 1 % R $end
$var wire 1 & S $end
$var reg 1 ' Q $end
$upscope $end
$scope module testbench $end
$var wire 1 ( valid_in $end
$var wire 1 ) reset $end
$var wire 1 * data_outSynth $end
$var wire 1 + data_outCond $end
$var wire 8 , data_in [7:0] $end
$var wire 1 - clk_4f $end
$var wire 1 . clk_32f $end
$scope module PSCond $end
$var wire 1 ( valid_in $end
$var wire 1 ) reset $end
$var wire 8 / data_in [7:0] $end
$var wire 1 - clk_4f $end
$var wire 1 . clk_32f $end
$var reg 8 0 contador [7:0] $end
$var reg 8 1 data2send [7:0] $end
$var reg 1 + data_out $end
$upscope $end
$scope module PSSynth $end
$var wire 1 ( valid_in $end
$var wire 1 ) reset $end
$var wire 1 * data_out $end
$var wire 8 2 data_in [7:0] $end
$var wire 8 3 contador [7:0] $end
$var wire 1 - clk_4f $end
$var wire 1 . clk_32f $end
$var wire 1 4 _065_ $end
$var wire 1 5 _064_ $end
$var wire 1 6 _063_ $end
$var wire 1 7 _062_ $end
$var wire 1 8 _061_ $end
$var wire 1 9 _060_ $end
$var wire 1 : _059_ $end
$var wire 1 ; _058_ $end
$var wire 1 < _057_ $end
$var wire 1 = _056_ $end
$var wire 1 > _055_ $end
$var wire 1 ? _054_ $end
$var wire 1 @ _053_ $end
$var wire 1 A _052_ $end
$var wire 1 B _051_ $end
$var wire 1 C _050_ $end
$var wire 1 D _049_ $end
$var wire 1 E _048_ $end
$var wire 1 F _047_ $end
$var wire 1 G _046_ $end
$var wire 1 H _045_ $end
$var wire 1 I _044_ $end
$var wire 1 J _043_ $end
$var wire 1 K _042_ $end
$var wire 1 L _041_ $end
$var wire 1 M _040_ $end
$var wire 1 N _039_ $end
$var wire 1 O _038_ $end
$var wire 1 P _037_ $end
$var wire 1 Q _036_ $end
$var wire 1 R _035_ $end
$var wire 1 S _034_ $end
$var wire 1 T _033_ $end
$var wire 1 U _032_ $end
$var wire 1 V _031_ $end
$var wire 1 W _030_ $end
$var wire 1 X _029_ $end
$var wire 1 Y _028_ $end
$var wire 1 Z _027_ $end
$var wire 1 [ _026_ $end
$var wire 1 \ _025_ $end
$var wire 1 ] _024_ $end
$var wire 1 ^ _023_ $end
$var wire 1 _ _022_ $end
$var wire 1 ` _021_ $end
$var wire 1 a _020_ $end
$var wire 1 b _019_ $end
$var wire 1 c _018_ $end
$var wire 1 d _017_ $end
$var wire 1 e _016_ $end
$var wire 1 f _015_ $end
$var wire 1 g _014_ $end
$var wire 1 h _013_ $end
$var wire 1 i _012_ $end
$var wire 1 j _011_ $end
$var wire 1 k _010_ $end
$var wire 1 l _009_ $end
$var wire 1 m _008_ $end
$var wire 1 n _007_ $end
$var wire 1 o _006_ $end
$var wire 1 p _005_ $end
$var wire 1 q _004_ $end
$var wire 1 r _003_ $end
$var wire 1 s _002_ $end
$var wire 1 t _001_ $end
$var wire 8 u _000_ [7:0] $end
$scope module _066_ $end
$var wire 1 v A $end
$var wire 1 s Y $end
$upscope $end
$scope module _067_ $end
$var wire 1 w A $end
$var wire 1 r Y $end
$upscope $end
$scope module _068_ $end
$var wire 1 x A $end
$var wire 1 q Y $end
$upscope $end
$scope module _069_ $end
$var wire 1 y A $end
$var wire 1 p Y $end
$upscope $end
$scope module _070_ $end
$var wire 1 z A $end
$var wire 1 o Y $end
$upscope $end
$scope module _071_ $end
$var wire 1 { A $end
$var wire 1 n Y $end
$upscope $end
$scope module _072_ $end
$var wire 1 m Y $end
$var wire 1 ) A $end
$upscope $end
$scope module _073_ $end
$var wire 1 l Y $end
$var wire 1 ( A $end
$upscope $end
$scope module _074_ $end
$var wire 1 | A $end
$var wire 1 k Y $end
$upscope $end
$scope module _075_ $end
$var wire 1 } A $end
$var wire 1 j Y $end
$upscope $end
$scope module _076_ $end
$var wire 1 ~ B $end
$var wire 1 !" Y $end
$var wire 1 ) A $end
$upscope $end
$scope module _077_ $end
$var wire 1 "" A $end
$var wire 1 #" B $end
$var wire 1 i Y $end
$upscope $end
$scope module _078_ $end
$var wire 1 $" A $end
$var wire 1 %" B $end
$var wire 1 h Y $end
$upscope $end
$scope module _079_ $end
$var wire 1 h B $end
$var wire 1 g Y $end
$var wire 1 ) A $end
$upscope $end
$scope module _080_ $end
$var wire 1 i A $end
$var wire 1 g B $end
$var wire 1 f Y $end
$upscope $end
$scope module _081_ $end
$var wire 1 f A $end
$var wire 1 &" Y $end
$upscope $end
$scope module _082_ $end
$var wire 1 s A $end
$var wire 1 k B $end
$var wire 1 e Y $end
$upscope $end
$scope module _083_ $end
$var wire 1 '" A $end
$var wire 1 e B $end
$var wire 1 d Y $end
$upscope $end
$scope module _084_ $end
$var wire 1 d A $end
$var wire 1 c Y $end
$upscope $end
$scope module _085_ $end
$var wire 1 s A $end
$var wire 1 i B $end
$var wire 1 b Y $end
$upscope $end
$scope module _086_ $end
$var wire 1 m A $end
$var wire 1 b B $end
$var wire 1 a Y $end
$upscope $end
$scope module _087_ $end
$var wire 1 c A $end
$var wire 1 a B $end
$var wire 1 (" Y $end
$upscope $end
$scope module _088_ $end
$var wire 1 )" A $end
$var wire 1 c B $end
$var wire 1 ` Y $end
$upscope $end
$scope module _089_ $end
$var wire 1 r A $end
$var wire 1 d B $end
$var wire 1 _ Y $end
$upscope $end
$scope module _090_ $end
$var wire 1 r A $end
$var wire 1 d B $end
$var wire 1 ^ Y $end
$upscope $end
$scope module _091_ $end
$var wire 1 ` A $end
$var wire 1 ^ B $end
$var wire 1 ] Y $end
$upscope $end
$scope module _092_ $end
$var wire 1 *" A $end
$var wire 1 _ B $end
$var wire 1 \ Y $end
$upscope $end
$scope module _093_ $end
$var wire 1 \ A $end
$var wire 1 [ Y $end
$upscope $end
$scope module _094_ $end
$var wire 1 +" A $end
$var wire 1 [ B $end
$var wire 1 Z Y $end
$upscope $end
$scope module _095_ $end
$var wire 1 p A $end
$var wire 1 \ B $end
$var wire 1 Y Y $end
$upscope $end
$scope module _096_ $end
$var wire 1 ," A $end
$var wire 1 Y B $end
$var wire 1 X Y $end
$upscope $end
$scope module _097_ $end
$var wire 1 n A $end
$var wire 1 X B $end
$var wire 1 W Y $end
$upscope $end
$scope module _098_ $end
$var wire 1 -" A $end
$var wire 1 V Y $end
$var wire 1 ) B $end
$upscope $end
$scope module _099_ $end
$var wire 1 W B $end
$var wire 1 U Y $end
$var wire 1 ) A $end
$upscope $end
$scope module _100_ $end
$var wire 1 ] A $end
$var wire 1 U B $end
$var wire 1 ." Y $end
$upscope $end
$scope module _101_ $end
$var wire 1 q A $end
$var wire 1 ` B $end
$var wire 1 T Y $end
$upscope $end
$scope module _102_ $end
$var wire 1 \ A $end
$var wire 1 T B $end
$var wire 1 S Y $end
$upscope $end
$scope module _103_ $end
$var wire 1 U A $end
$var wire 1 S B $end
$var wire 1 /" Y $end
$upscope $end
$scope module _104_ $end
$var wire 1 p A $end
$var wire 1 \ B $end
$var wire 1 R Y $end
$upscope $end
$scope module _105_ $end
$var wire 1 Z A $end
$var wire 1 R B $end
$var wire 1 Q Y $end
$upscope $end
$scope module _106_ $end
$var wire 1 U A $end
$var wire 1 Q B $end
$var wire 1 0" Y $end
$upscope $end
$scope module _107_ $end
$var wire 1 o A $end
$var wire 1 Z B $end
$var wire 1 P Y $end
$upscope $end
$scope module _108_ $end
$var wire 1 X A $end
$var wire 1 P B $end
$var wire 1 O Y $end
$upscope $end
$scope module _109_ $end
$var wire 1 U A $end
$var wire 1 O B $end
$var wire 1 1" Y $end
$upscope $end
$scope module _110_ $end
$var wire 1 X A $end
$var wire 1 V B $end
$var wire 1 2" Y $end
$upscope $end
$scope module _111_ $end
$var wire 1 3" A $end
$var wire 1 e B $end
$var wire 1 N Y $end
$upscope $end
$scope module _112_ $end
$var wire 1 s A $end
$var wire 1 4" B $end
$var wire 1 M Y $end
$upscope $end
$scope module _113_ $end
$var wire 1 5" A $end
$var wire 1 M B $end
$var wire 1 L Y $end
$upscope $end
$scope module _114_ $end
$var wire 1 N A $end
$var wire 1 L B $end
$var wire 1 K Y $end
$upscope $end
$scope module _115_ $end
$var wire 1 6" A $end
$var wire 1 7" B $end
$var wire 1 J Y $end
$upscope $end
$scope module _116_ $end
$var wire 1 8" A $end
$var wire 1 J B $end
$var wire 1 I Y $end
$upscope $end
$scope module _117_ $end
$var wire 1 9" A $end
$var wire 1 k B $end
$var wire 1 H Y $end
$upscope $end
$scope module _118_ $end
$var wire 1 :" A $end
$var wire 1 H B $end
$var wire 1 G Y $end
$upscope $end
$scope module _119_ $end
$var wire 1 I A $end
$var wire 1 G B $end
$var wire 1 F Y $end
$upscope $end
$scope module _120_ $end
$var wire 1 K A $end
$var wire 1 F B $end
$var wire 1 E Y $end
$upscope $end
$scope module _121_ $end
$var wire 1 j A $end
$var wire 1 E B $end
$var wire 1 D Y $end
$upscope $end
$scope module _122_ $end
$var wire 1 ;" A $end
$var wire 1 M B $end
$var wire 1 C Y $end
$upscope $end
$scope module _123_ $end
$var wire 1 <" A $end
$var wire 1 J B $end
$var wire 1 B Y $end
$upscope $end
$scope module _124_ $end
$var wire 1 =" A $end
$var wire 1 H B $end
$var wire 1 A Y $end
$upscope $end
$scope module _125_ $end
$var wire 1 B A $end
$var wire 1 A B $end
$var wire 1 @ Y $end
$upscope $end
$scope module _126_ $end
$var wire 1 >" A $end
$var wire 1 J B $end
$var wire 1 ? Y $end
$upscope $end
$scope module _127_ $end
$var wire 1 ?" A $end
$var wire 1 > Y $end
$var wire 1 ( B $end
$upscope $end
$scope module _128_ $end
$var wire 1 e A $end
$var wire 1 > B $end
$var wire 1 = Y $end
$upscope $end
$scope module _129_ $end
$var wire 1 ? A $end
$var wire 1 = B $end
$var wire 1 < Y $end
$upscope $end
$scope module _130_ $end
$var wire 1 @" A $end
$var wire 1 e B $end
$var wire 1 ; Y $end
$upscope $end
$scope module _131_ $end
$var wire 1 C A $end
$var wire 1 ; B $end
$var wire 1 : Y $end
$upscope $end
$scope module _132_ $end
$var wire 1 @ A $end
$var wire 1 : B $end
$var wire 1 9 Y $end
$upscope $end
$scope module _133_ $end
$var wire 1 A" A $end
$var wire 1 9 B $end
$var wire 1 8 Y $end
$upscope $end
$scope module _134_ $end
$var wire 1 8 A $end
$var wire 1 7 Y $end
$upscope $end
$scope module _135_ $end
$var wire 1 B" A $end
$var wire 1 l B $end
$var wire 1 6 Y $end
$upscope $end
$scope module _136_ $end
$var wire 1 D A $end
$var wire 1 6 B $end
$var wire 1 5 Y $end
$upscope $end
$scope module _137_ $end
$var wire 1 7 A $end
$var wire 1 5 B $end
$var wire 1 4 Y $end
$upscope $end
$scope module _138_ $end
$var wire 1 < A $end
$var wire 1 4 B $end
$var wire 1 t Y $end
$upscope $end
$scope module _139_ $end
$var wire 1 m A $end
$var wire 1 t B $end
$var wire 1 * Y $end
$upscope $end
$scope module _140_ $end
$var wire 1 C" D $end
$var wire 1 . C $end
$var reg 1 D" Q $end
$upscope $end
$scope module _141_ $end
$var wire 1 E" D $end
$var wire 1 . C $end
$var reg 1 F" Q $end
$upscope $end
$scope module _142_ $end
$var wire 1 G" D $end
$var wire 1 . C $end
$var reg 1 H" Q $end
$upscope $end
$scope module _143_ $end
$var wire 1 I" D $end
$var wire 1 . C $end
$var reg 1 J" Q $end
$upscope $end
$scope module _144_ $end
$var wire 1 K" D $end
$var wire 1 . C $end
$var reg 1 L" Q $end
$upscope $end
$scope module _145_ $end
$var wire 1 M" D $end
$var wire 1 . C $end
$var reg 1 N" Q $end
$upscope $end
$scope module _146_ $end
$var wire 1 O" D $end
$var wire 1 . C $end
$var reg 1 P" Q $end
$upscope $end
$scope module _147_ $end
$var wire 1 Q" D $end
$var wire 1 . C $end
$var reg 1 R" Q $end
$upscope $end
$upscope $end
$scope module probador $end
$var wire 1 + data_outCond $end
$var wire 1 * data_outSynth $end
$var reg 1 . clk_32f $end
$var reg 1 - clk_4f $end
$var reg 8 S" data_in [7:0] $end
$var reg 1 ) reset $end
$var reg 1 ( valid_in $end
$upscope $end
$upscope $end
$enddefinitions $end
#0
$dumpvars
b0 S"
xR"
0Q"
xP"
0O"
xN"
0M"
xL"
0K"
xJ"
0I"
xH"
1G"
xF"
1E"
xD"
1C"
xB"
xA"
0@"
x?"
x>"
0="
0<"
0;"
0:"
x9"
08"
x7"
x6"
05"
x4"
03"
02"
01"
00"
0/"
0."
x-"
x,"
x+"
x*"
x)"
1("
x'"
1&"
x%"
x$"
x#"
x""
1!"
x~
x}
x|
x{
xz
xy
xx
xw
xv
b111 u
xt
xs
xr
xq
xp
xo
xn
1m
1l
xk
xj
xi
xh
1g
0f
xe
xd
xc
xb
0a
x`
x_
x^
x]
x\
x[
xZ
xY
xX
xW
1V
1U
xT
xS
xR
xQ
xP
xO
xN
xM
xL
xK
xJ
xI
xH
xG
xF
xE
xD
xC
xB
xA
x@
x?
x>
x=
x<
x;
x:
x9
x8
x7
06
15
04
bx 3
b0 2
b0 1
b111 0
b0 /
1.
0-
b0 ,
0+
0*
0)
0(
x'
z&
z%
z$
z#
z"
z!
$end
#4
0.
#8
1W
1O
17
1Q
08
0X
0t
0Z
1E
19
1Y
1S
1K
1:
1]
1<
1[
0F
0@
0\
0L
0C
0N
0;
0`
0=
0G
0A
1I
1B
0P
0R
0T
1_
0^
1b
1M
1e
1c
1D
1>
1H
0J
0?
0d
0h
0i
1n
1o
1p
1q
1r
0s
0k
0j
0-"
0{
0,"
0z
0+"
0y
0*"
0x
0B"
0?"
0)"
0w
19"
16"
1v
17"
14"
1$"
1""
1|
1A"
1>"
1'"
1%"
1#"
1~
1}
0R"
0P"
0N"
0L"
0J"
1H"
1F"
b111 3
1D"
1.
#12
0.
#16
1.
#20
0.
#24
1.
#28
0.
#32
0C"
1*
0U
b110 u
0!"
0m
1+
b10111100 1
1)
1.
1-
#36
0.
#40
0*
0E"
0&"
1t
1f
0<
0g
07
1C"
0D
18
1?
1h
b101 u
1!"
1j
0A"
0>"
0'"
0%"
0#"
0~
0}
0+
b10111100 1
b110 3
0D"
b110 0
1.
#44
0.
#48
1*
0t
1G
1A
1<
0I
0B
17
0C"
1D
0H
08
0?
b100 u
0!"
1J
0j
1k
1+
b10111100 1
1A"
1>"
1'"
1%"
1#"
1~
1}
07"
04"
0$"
0""
0|
b101 0
1D"
b101 3
0F"
1.
#52
0.
#56
0G"
0("
1E"
1a
1&"
0f
0b
07
1C"
0D
18
1i
b11 u
1!"
1j
0A"
0>"
0'"
0%"
0#"
0~
0}
1+
b10111100 1
b100 3
0D"
b100 0
1.
#60
0.
#64
0K
0:
1E"
1F
1@
1&"
1L
1C
1g
0f
0G
0A
17
0C"
1D
08
b10 u
0!"
0M
0h
0i
1H
0j
0k
1s
1+
b10111100 1
1A"
1>"
1'"
1%"
1#"
1~
1}
17"
14"
1$"
1""
1|
09"
06"
0v
b11 0
1D"
1F"
b11 3
0H"
1.
0-
#68
0.
#72
0E"
0&"
1f
0g
07
1C"
0D
18
1h
b1 u
1!"
1j
0A"
0>"
0'"
0%"
0#"
0~
0}
1+
b10111100 1
b10 3
0D"
b10 0
1.
#76
0.
#80
0*
1t
0<
1N
1=
1;
0L
0C
17
0C"
1D
0e
08
b0 u
0!"
1M
0j
1k
0+
b10111100 1
1A"
1>"
1'"
1%"
1#"
1~
1}
07"
04"
0$"
0""
0|
b1 0
1D"
b1 3
0F"
1.
#84
0.
#88
0O"
0M"
1U
01"
00"
0W
0O
0Q
0K"
0I"
1X
0/"
0."
1Z
0Y
0S
0]
0[
1G"
1\
1E"
1("
1`
1&"
0_
0f
07
0c
1C"
0D
18
1d
1i
b111 u
1!"
1j
0A"
0>"
0'"
0%"
0#"
0~
0}
b10111100 1
b0 3
0D"
b0 0
1.
#92
0.
#96
0U
1W
1O
1Q
1*
0X
0Z
09
0t
1Y
1S
1]
1[
1<
1:
1G"
0\
1E"
0a
1@
0F
1E
1("
0`
1&"
0=
0;
1_
1g
0f
1b
0A
1I
1K
07
1c
0C"
1D
1e
18
0d
b110 u
0!"
0h
0i
1H
0J
0N
0j
0k
0s
1A"
1>"
1'"
1%"
1#"
1~
1}
17"
14"
1$"
1""
1|
19"
16"
1v
1<"
1;"
1:"
15"
13"
1+
b10111100 1
b111 0
1D"
1F"
b111 3
1H"
b10011101 ,
b10011101 /
b10011101 2
b10011101 S"
1.
1-
#100
0.
#104
0*
0E"
0&"
1t
1f
0<
0g
1C"
0D
1?
1h
b101 u
1!"
1j
0A"
0>"
0'"
0%"
0#"
0~
0}
0+
b10111100 1
b110 3
0D"
b110 0
1.
#108
0.
#112
17
08
19
1*
0E
0@
0t
1F
1A
1<
0I
0C"
1D
0H
0?
b100 u
0!"
1J
0j
1k
1+
b10111100 1
1A"
1>"
1'"
1%"
1#"
1~
1}
07"
04"
0$"
0""
0|
b101 0
1D"
b101 3
0F"
1.
#116
0.
