Proyecto2/arbitro2/probador.v
module probador(
    output reg reset, clk, active,
    output reg [11:0] demuxin,
    output reg emptyFIFO,
    output reg [3:0] almost_fullFIFO, 
    input pop, popSynth,
    input [3:0] push, pushSynth);

    initial clk <= 0;
    always #1 clk <= ~clk;
    
    initial begin
        $dumpfile("verificacion.vcd");
        $dumpvars();

        reset <= 0;
        active <= 0;
        demuxin <= 0;
        emptyFIFO <= 0;
        almost_fullFIFO <= 0;

        @(posedge clk);

        @(posedge clk);
        reset <= 1;
        emptyFIFO <= 1;

        @(posedge clk);

        @(posedge clk);
        active <= 1;

        @(posedge clk);

        @(posedge clk);
        demuxin <= 'h0AB;

        @(posedge clk);
        demuxin <= 'h4AB;

        @(posedge clk);
        demuxin <= 'h8AB;

        @(posedge clk);
        demuxin <= 'hFAB;

        @(posedge clk);
        demuxin <= 'h0DE;

        @(posedge clk);
        demuxin <= 'h4DE;

        @(posedge clk);
        demuxin <= 'h8DE;

        @(posedge clk);
        demuxin <= 'hFDE;

        @(posedge clk);
        emptyFIFO <= 0;

        @(posedge clk);
        demuxin <= 'h074;

        @(posedge clk);
        demuxin <= 'h474;

        @(posedge clk);
        demuxin <= 'h974;

        @(posedge clk);
        demuxin <= 'hE43;

        @(posedge clk);
        almost_fullFIFO <= 'b1000;

        @(posedge clk);
        almost_fullFIFO <= 'b1100;

        @(posedge clk);
        almost_fullFIFO <= 'b1110;

        #5 $finish;
    end 
endmodule

Proyecto2/arbitro2/arbitro2Synth.v
/* Generated by Yosys 0.9 (git sha1 1979e0b) */

(* top =  1  *)
(* src = "arbitro2Synth.v:1" *)
module arbitro2Synth(reset, clk, active, demuxin, emptyFIFO, almost_fullFIFO, pop, push);
  wire _00_;
  wire _01_;
  wire _02_;
  wire _03_;
  wire _04_;
  wire _05_;
  wire _06_;
  wire _07_;
  wire _08_;
  wire _09_;
  wire _10_;
  wire _11_;
  wire _12_;
  wire _13_;
  wire _14_;
  wire _15_;
  wire _16_;
  wire _17_;
  wire _18_;
  wire _19_;
  wire _20_;
  wire _21_;
  wire _22_;
  (* src = "arbitro2Synth.v:2" *)
  input active;
  (* src = "arbitro2Synth.v:5" *)
  input [3:0] almost_fullFIFO;
  (* src = "arbitro2Synth.v:2" *)
  input clk;
  (* src = "arbitro2Synth.v:3" *)
  input [11:0] demuxin;
  (* src = "arbitro2Synth.v:4" *)
  input emptyFIFO;
  (* src = "arbitro2Synth.v:6" *)
  output pop;
  (* src = "arbitro2Synth.v:7" *)
  output [3:0] push;
  (* src = "arbitro2Synth.v:2" *)
  input reset;
  NOT _23_ (
    .A(demuxin[10]),
    .Y(_00_)
  );
  NOR _24_ (
    .A(demuxin[6]),
    .B(demuxin[7]),
    .Y(_01_)
  );
  NOR _25_ (
    .A(demuxin[8]),
    .B(demuxin[9]),
    .Y(_02_)
  );
  NAND _26_ (
    .A(_01_),
    .B(_02_),
    .Y(_03_)
  );
  NOR _27_ (
    .A(demuxin[0]),
    .B(demuxin[1]),
    .Y(_04_)
  );
  NOR _28_ (
    .A(demuxin[2]),
    .B(demuxin[5]),
    .Y(_05_)
  );
  NAND _29_ (
    .A(_04_),
    .B(_05_),
    .Y(_06_)
  );
  NOT _30_ (
    .A(_06_),
    .Y(_07_)
  );
  NOR _31_ (
    .A(demuxin[3]),
    .B(demuxin[4]),
    .Y(_08_)
  );
  NOT _32_ (
    .A(_08_),
    .Y(_09_)
  );
  NOR _33_ (
    .A(_03_),
    .B(_09_),
    .Y(_10_)
  );
  NAND _34_ (
    .A(_07_),
    .B(_10_),
    .Y(_11_)
  );
  NOR _35_ (
    .A(almost_fullFIFO[0]),
    .B(almost_fullFIFO[1]),
    .Y(_12_)
  );
  NOR _36_ (
    .A(almost_fullFIFO[2]),
    .B(almost_fullFIFO[3]),
    .Y(_13_)
  );
  NOT _37_ (
    .A(_13_),
    .Y(_14_)
  );
  NAND _38_ (
    .A(active),
    .B(reset),
    .Y(_15_)
  );
  NOR _39_ (
    .A(_14_),
    .B(_15_),
    .Y(_16_)
  );
  NAND _40_ (
    .A(_12_),
    .B(_16_),
    .Y(_17_)
  );
  NOT _41_ (
    .A(_17_),
    .Y(_18_)
  );
  NOR _42_ (
    .A(demuxin[11]),
    .B(_17_),
    .Y(_19_)
  );
  NAND _43_ (
    .A(_11_),
    .B(_19_),
    .Y(_20_)
  );
  NOR _44_ (
    .A(demuxin[10]),
    .B(_20_),
    .Y(push[0])
  );
  NAND _45_ (
    .A(demuxin[10]),
    .B(_19_),
    .Y(_21_)
  );
  NOT _46_ (
    .A(_21_),
    .Y(push[1])
  );
  NAND _47_ (
    .A(demuxin[11]),
    .B(_18_),
    .Y(_22_)
  );
  NOR _48_ (
    .A(demuxin[10]),
    .B(_22_),
    .Y(push[2])
  );
  NOR _49_ (
    .A(_00_),
    .B(_22_),
    .Y(push[3])
  );
  NOR _50_ (
    .A(emptyFIFO),
    .B(_17_),
    .Y(pop)
  );
endmodule

Proyecto2/QoS_PCIE/arbitro2.v
module arbitro2(
    input reset, clk, active,
    input [11:0] demuxin,
    input emptyFIFO,
    input [3:0] almost_fullFIFO, 
    output reg pop,
    output reg [3:0] push);

    always @(*) begin
        pop = 0;
        push = 0;

        if (reset == 0 || active == 0) begin
            pop = 0; 
            push = 0;
        end
        
        else if (almost_fullFIFO != 0) begin
            pop = 0;
            push = 0;
        end 

//Si class = 00, el push del canal P0 es 1, caso contrario es 0. 
//class = 01, push canal P1 es 1, etc...
        else begin
            if (emptyFIFO == 1) begin
                pop = 0; 
                if (demuxin[11:10] == 'b00 && demuxin != 0) push[0] = 1;
                else push[0] = 0;

                if (demuxin[11:10] == 'b01 && demuxin != 0) push[1] = 1;
                else push[1] = 0;

                if (demuxin[11:10] == 'b10 && demuxin != 0) push[2] = 1;
                else push[2] = 0;

                if (demuxin[11:10] == 'b11 && demuxin != 0) push[3] = 1;
                else push[3] = 0;
            end
            else begin
                pop = 1;
                if (demuxin[11:10] == 'b00 && demuxin != 0) push[0] = 1;
                else push[0] = 0;

                if (demuxin[11:10] == 'b01 && demuxin != 0) push[1] = 1;
                else push[1] = 0;

                if (demuxin[11:10] == 'b10 && demuxin != 0) push[2] = 1;
                else push[2] = 0;

                if (demuxin[11:10] == 'b11 && demuxin != 0) push[3] = 1;
                else push[3] = 0; 
            end 
        end
    end
endmodule

Proyecto2/arbitro2/testbench.v
`include "arbitro2.v"
`include "arbitro2Synth.v"
`include "probador.v"
`include "cmos_cells.v"

module testbench();

wire [3:0] almost_fullFIFO, push, pushSynth;
wire [11:0] demuxin;
wire reset, clk, active, emptyFIFO, pop, popSynth;

arbitro2 arbitroCond (/*AUTOINST*/
		      // Outputs
		      .pop		(pop),
		      .push		(push[3:0]),
		      // Inputs
		      .reset		(reset),
		      .clk		(clk),
			  .active (active),
		      .demuxin		(demuxin[11:0]),
		      .emptyFIFO	(emptyFIFO),
		      .almost_fullFIFO	(almost_fullFIFO[3:0]));

arbitro2Synth arbitroSynth (/*AUTOINST*/
			    // Outputs
			    .pop		(popSynth),
			    .push		(pushSynth[3:0]),
			    // Inputs
			    .almost_fullFIFO	(almost_fullFIFO[3:0]),
			    .clk		(clk),
				.active (active),
			    .emptyFIFO		(emptyFIFO),
			    .demuxin		(demuxin[11:0]),
			    .reset		(reset));

probador probador (/*AUTOINST*/
		   // Outputs
		   .reset		(reset),
		   .clk			(clk),
		   .active (active),
		   .demuxin		(demuxin[11:0]),
		   .emptyFIFO		(emptyFIFO),
		   .almost_fullFIFO	(almost_fullFIFO[3:0]),
		   // Inputs
		   .pop			(pop),
		   .popSynth		(popSynth),
		   .push		(push[3:0]),
		   .pushSynth		(pushSynth[3:0]));

endmodule

Tarea5/cmos_cellsRetardos.v
module BUF(A, Y);
input A;
output Y;
assign #(1:2.4:3.5, 1:2.4:3.5) Y = A;
endmodule

module NOT(A, Y);
input A;
output Y;
assign #(0.7:2:3.3, 0.7:2:3.3) Y = ~A;
endmodule

module NAND(A, B, Y);
input A, B;
output Y;
assign #(1:2.4:3.5, 1:2.4:3.5) Y = ~(A & B);
endmodule

module NOR(A, B, Y);
input A, B;
output Y;
assign #(0.9:2.25:3.6, 0.9:2.25:3.6) Y = ~(A | B);
endmodule

module DFF(C, D, Q);
input C, D;
output reg Q;
always @(posedge C)
	Q <= D;
endmodule

module DFFSR(C, D, Q, S, R);
input C, D, S, R;
output reg Q;
always @(posedge C, posedge S, posedge R)
	if (S)
		Q <= 1'b1;
	else if (R)
		Q <= 1'b0;
	else
		Q <= D;
endmodule

Proyecto2/arbitro2/verificacion.vcd
$date
	Fri Nov 26 23:17:32 2021
$end
$version
	Icarus Verilog
$end
$timescale
	1s
$end
$scope module BUF $end
$var wire 1 ! A $end
$var wire 1 " Y $end
$upscope $end
$scope module DFF $end
$var wire 1 # C $end
$var wire 1 $ D $end
$var reg 1 % Q $end
$upscope $end
$scope module DFFSR $end
$var wire 1 & C $end
$var wire 1 ' D $end
$var wire 1 ( R $end
$var wire 1 ) S $end
$var reg 1 * Q $end
$upscope $end
$scope module testbench $end
$var wire 1 + reset $end
$var wire 4 , pushSynth [3:0] $end
$var wire 4 - push [3:0] $end
$var wire 1 . popSynth $end
$var wire 1 / pop $end
$var wire 1 0 emptyFIFO $end
$var wire 12 1 demuxin [11:0] $end
$var wire 1 2 clk $end
$var wire 4 3 almost_fullFIFO [3:0] $end
$var wire 1 4 active $end
$scope module arbitroCond $end
$var wire 1 + reset $end
$var wire 1 0 emptyFIFO $end
$var wire 12 5 demuxin [11:0] $end
$var wire 1 2 clk $end
$var wire 4 6 almost_fullFIFO [3:0] $end
$var wire 1 4 active $end
$var reg 1 / pop $end
$var reg 4 7 push [3:0] $end
$upscope $end
$scope module arbitroSynth $end
$var wire 1 + reset $end
$var wire 4 8 push [3:0] $end
$var wire 1 . pop $end
$var wire 1 0 emptyFIFO $end
$var wire 12 9 demuxin [11:0] $end
$var wire 1 2 clk $end
$var wire 4 : almost_fullFIFO [3:0] $end
$var wire 1 4 active $end
$var wire 1 ; _22_ $end
$var wire 1 < _21_ $end
$var wire 1 = _20_ $end
$var wire 1 > _19_ $end
$var wire 1 ? _18_ $end
$var wire 1 @ _17_ $end
$var wire 1 A _16_ $end
$var wire 1 B _15_ $end
$var wire 1 C _14_ $end
$var wire 1 D _13_ $end
$var wire 1 E _12_ $end
$var wire 1 F _11_ $end
$var wire 1 G _10_ $end
$var wire 1 H _09_ $end
$var wire 1 I _08_ $end
$var wire 1 J _07_ $end
$var wire 1 K _06_ $end
$var wire 1 L _05_ $end
$var wire 1 M _04_ $end
$var wire 1 N _03_ $end
$var wire 1 O _02_ $end
$var wire 1 P _01_ $end
$var wire 1 Q _00_ $end
$scope module _23_ $end
$var wire 1 R A $end
$var wire 1 Q Y $end
$upscope $end
$scope module _24_ $end
$var wire 1 S A $end
$var wire 1 T B $end
$var wire 1 P Y $end
$upscope $end
$scope module _25_ $end
$var wire 1 U A $end
$var wire 1 V B $end
$var wire 1 O Y $end
$upscope $end
$scope module _26_ $end
$var wire 1 P A $end
$var wire 1 O B $end
$var wire 1 N Y $end
$upscope $end
$scope module _27_ $end
$var wire 1 W A $end
$var wire 1 X B $end
$var wire 1 M Y $end
$upscope $end
$scope module _28_ $end
$var wire 1 Y A $end
$var wire 1 Z B $end
$var wire 1 L Y $end
$upscope $end
$scope module _29_ $end
$var wire 1 M A $end
$var wire 1 L B $end
$var wire 1 K Y $end
$upscope $end
$scope module _30_ $end
$var wire 1 K A $end
$var wire 1 J Y $end
$upscope $end
$scope module _31_ $end
$var wire 1 [ A $end
$var wire 1 \ B $end
$var wire 1 I Y $end
$upscope $end
$scope module _32_ $end
$var wire 1 I A $end
$var wire 1 H Y $end
$upscope $end
$scope module _33_ $end
$var wire 1 N A $end
$var wire 1 H B $end
$var wire 1 G Y $end
$upscope $end
$scope module _34_ $end
$var wire 1 J A $end
$var wire 1 G B $end
$var wire 1 F Y $end
$upscope $end
$scope module _35_ $end
$var wire 1 ] A $end
$var wire 1 ^ B $end
$var wire 1 E Y $end
$upscope $end
$scope module _36_ $end
$var wire 1 _ A $end
$var wire 1 ` B $end
$var wire 1 D Y $end
$upscope $end
$scope module _37_ $end
$var wire 1 D A $end
$var wire 1 C Y $end
$upscope $end
$scope module _38_ $end
$var wire 1 B Y $end
$var wire 1 + B $end
$var wire 1 4 A $end
$upscope $end
$scope module _39_ $end
$var wire 1 C A $end
$var wire 1 B B $end
$var wire 1 A Y $end
$upscope $end
$scope module _40_ $end
$var wire 1 E A $end
$var wire 1 A B $end
$var wire 1 @ Y $end
$upscope $end
$scope module _41_ $end
$var wire 1 @ A $end
$var wire 1 ? Y $end
$upscope $end
$scope module _42_ $end
$var wire 1 a A $end
$var wire 1 @ B $end
$var wire 1 > Y $end
$upscope $end
$scope module _43_ $end
$var wire 1 F A $end
$var wire 1 > B $end
$var wire 1 = Y $end
$upscope $end
$scope module _44_ $end
$var wire 1 b A $end
$var wire 1 = B $end
$var wire 1 c Y $end
$upscope $end
$scope module _45_ $end
$var wire 1 d A $end
$var wire 1 > B $end
$var wire 1 < Y $end
$upscope $end
$scope module _46_ $end
$var wire 1 < A $end
$var wire 1 e Y $end
$upscope $end
$scope module _47_ $end
$var wire 1 f A $end
$var wire 1 ? B $end
$var wire 1 ; Y $end
$upscope $end
$scope module _48_ $end
$var wire 1 g A $end
$var wire 1 ; B $end
$var wire 1 h Y $end
$upscope $end
$scope module _49_ $end
$var wire 1 Q A $end
$var wire 1 ; B $end
$var wire 1 i Y $end
$upscope $end
$scope module _50_ $end
$var wire 1 @ B $end
$var wire 1 . Y $end
$var wire 1 0 A $end
$upscope $end
$upscope $end
$scope module probador $end
$var wire 1 / pop $end
$var wire 1 . popSynth $end
$var wire 4 j push [3:0] $end
$var wire 4 k pushSynth [3:0] $end
$var reg 1 4 active $end
$var reg 4 l almost_fullFIFO [3:0] $end
$var reg 1 2 clk $end
$var reg 12 m demuxin [11:0] $end
$var reg 1 0 emptyFIFO $end
$var reg 1 + reset $end
$upscope $end
$upscope $end
$enddefinitions $end
#0
$dumpvars
b0 m
b0 l
b0 k
b0 j
0i
0h
0g
0f
0e
0d
0c
0b
0a
0`
0_
0^
0]
0\
0[
0Z
0Y
0X
0W
0V
0U
0T
0S
0R
1Q
1P
1O
0N
1M
1L
0K
1J
1I
0H
1G
0F
1E
1D
0C
1B
0A
1@
0?
0>
1=
1<
1;
b0 :
b0 9
b0 8
b0 7
b0 6
b0 5
04
b0 3
02
b0 1
00
0/
0.
b0 -
b0 ,
0+
x*
z)
z(
z'
z&
x%
z$
z#
z"
z!
$end
#1
12
#2
02
#3
10
1+
12
#4
02
#5
12
#6
02
#7
1>
1?
0@
1A
0B
14
12
#8
02
#9
12
#10
02
#11
b1 ,
b1 8
b1 k
1c
0=
1F
0G
0J
1K
1N
1H
0I
0L
0M
0P
1[
1Z
1X
1W
1T
b1 -
b1 7
b1 j
b10101011 1
b10101011 5
b10101011 9
b10101011 m
12
#12
02
#13
1e
0<
b10 ,
b10 8
b10 k
0c
0Q
1g
1d
1b
1R
b10 -
b10 7
b10 j
b10010101011 1
b10010101011 5
b10010101011 9
b10010101011 m
12
#14
02
#15
1h
1=
0e
0;
1<
b100 ,
b100 8
b100 k
0c
0>
1Q
0g
1f
0d
0b
1a
0R
b100 -
b100 7
b100 j
b100010101011 1
b100010101011 5
b100010101011 9
b100010101011 m
12
#16
02
#17
1i
b1000 ,
b1000 8
b1000 k
0h
0O
0Q
1g
1d
1b
1V
1U
1R
b1000 -
b1000 7
b1000 j
b111110101011 1
b111110101011 5
b111110101011 9
b111110101011 m
12
#18
02
#19
1c
0=
0i
b1 ,
b1 8
b1 k
0h
1;
1>
1O
1Q
0g
0f
0d
0b
0a
1\
0Z
1Y
0W
0V
0U
1S
0R
b1 -
b1 7
b1 j
b11011110 1
b11011110 5
b11011110 9
b11011110 m
12
#20
02
#21
1e
0<
b10 ,
b10 8
b10 k
0c
0Q
1g
1d
1b
1R
b10 -
b10 7
b10 j
b10011011110 1
b10011011110 5
b10011011110 9
b10011011110 m
12
#22
02
#23
1h
1=
0e
0;
1<
b100 ,
b100 8
b100 k
0c
0>
1Q
0g
1f
0d
0b
1a
0R
b100 -
b100 7
b100 j
b100011011110 1
b100011011110 5
b100011011110 9
b100011011110 m
12
#24
02
#25
1i
b1000 ,
b1000 8
b1000 k
0h
0O
0Q
1g
1d
1b
1V
1U
1R
b1000 -
b1000 7
b1000 j
b111111011110 1
b111111011110 5
b111111011110 9
b111111011110 m
12
#26
02
#27
1.
1/
b1000 -
b1000 7
b1000 j
00
12
#28
02
#29
1c
0=
0i
b1 ,
b1 8
b1 k
0h
1;
1>
1M
1O
1Q
0g
0f
0d
0b
0a
0[
1Z
0X
0V
0U
0T
0R
b1 -
b1 7
b1 j
1/
b1110100 1
b1110100 5
b1110100 9
b1110100 m
12
#30
02
#31
1e
0<
b10 ,
b10 8
b10 k
0c
0Q
1g
1d
1b
1R
b10 -
b10 7
b10 j
1/
b10001110100 1
b10001110100 5
b10001110100 9
b10001110100 m
12
#32
02
#33
1h
1=
0e
0;
1<
b100 ,
b100 8
b100 k
0c
0>
0O
1Q
0g
1f
0d
0b
1a
1U
0R
b100 -
b100 7
b100 j
1/
b100101110100 1
b100101110100 5
b100101110100 9
b100101110100 m
12
#34
02
#35
0H
1i
b1000 ,
b1000 8
b1000 k
0h
1I
1L
0M
0Q
1g
1d
1b
0\
0Z
0Y
1X
1W
1V
0U
1R
b1000 -
b1000 7
b1000 j
1/
b111001000011 1
b111001000011 5
b111001000011 9
b111001000011 m
12
#36
02
#37
b0 ,
b0 8
b0 k
0i
1;
0.
0?
1@
0A
1C
0D
1`
b0 -
b0 7
b0 j
0/
b1000 3
b1000 6
b1000 :
b1000 l
12
#38
02
#39
1_
b1100 3
b1100 6
b1100 :
b1100 l
12
#40
02
#41
0E
1^
b1110 3
b1110 6
b1110 :
b1110 l
12
