Tarea 2/testbenchMuxMem.v
module testbenchMuxMem(

	output reg clk,
	output reg reset_L,
	output reg selector,
	output reg [1:0] data_in0,
	output reg [1:0] data_in1,
	input [1:0] data_out);
	
	initial clk <= 0;     /*Inicialización del clock*/
    always #2 clk <= ~clk;

    initial 
    begin 
        $dumpfile("pruebamuxmem.vcd"); /*En este archivo se guardan todos los valores de la simulación*/
        $dumpvars;

        reset_L = 0;
        selector = 0;
        data_in0 = 0;
        data_in1 = 0;

        @(posedge clk);
        reset_L <= 1;

        @(posedge clk);
        data_in0 <= 3;
        data_in1 <= 2;

        @(posedge clk);
        selector <= 1;
        data_in0 <= 1;
        data_in1 <= 0;

        @(posedge clk);
        data_in0 <= 0;
        data_in1 <= 2;

        @(posedge clk);
        selector <= 0;
        data_in0 <= 0;
        data_in1 <= 1;

        @(posedge clk);
        data_in0 <= 3;
        data_in1 <= 2;

        #5 $finish;
    end
endmodule

Tarea 2/muxmemoriaconductual.v
module mux_mem_conductual(

	input clk,
	input reset_L,
	input selector,
	input [1:0] data_in0,
	input [1:0] data_in1,
	output reg [1:0] data_out);
	
	reg [1:0] mout;
	
	always @ (*)
	begin 
		if (~selector) mout = data_in0;
		else mout = data_in1;
	end
	
	always @ (posedge clk)
	begin
		if (~reset_L) data_out <= 0;
		else data_out <= mout;
	end
		
endmodule

Tarea 2/probadorMuxMem.v
`include "muxmemoriaconductual.v"
`include "testbenchMuxMem.v"

module probadorMuxMem();

wire clk, reset_L, selector;
wire [1:0] data_in0, data_in1, data_out;

mux_mem_conductual mux1 (.clk(clk), .reset_L(reset_L), .selector(selector), .data_in0(data_in0), .data_in1(data_in1), .data_out(data_out));
testbenchMuxMem pruebamux (.clk(clk), .reset_L(reset_L), .selector(selector), .data_in0(data_in0), .data_in1(data_in1), .data_out(data_out));

endmodule

Tarea2/pruebamuxmem.vcd
$date
	Mon Aug 30 15:32:14 2021
$end
$version
	Icarus Verilog
$end
$timescale
	1s
$end
$scope module probadorMuxMem $end
$var wire 1 ! selector $end
$var wire 1 " reset_L $end
$var wire 2 # data_out [1:0] $end
$var wire 2 $ data_in1 [1:0] $end
$var wire 2 % data_in0 [1:0] $end
$var wire 1 & clk $end
$scope module mux1 $end
$var wire 1 ! selector $end
$var wire 1 " reset_L $end
$var wire 2 ' data_in1 [1:0] $end
$var wire 2 ( data_in0 [1:0] $end
$var wire 1 & clk $end
$var reg 2 ) data_out [1:0] $end
$var reg 2 * mout [1:0] $end
$upscope $end
$scope module pruebamux $end
$var wire 2 + data_out [1:0] $end
$var reg 1 & clk $end
$var reg 2 , data_in0 [1:0] $end
$var reg 2 - data_in1 [1:0] $end
$var reg 1 " reset_L $end
$var reg 1 ! selector $end
$upscope $end
$upscope $end
$enddefinitions $end
#0
$dumpvars
b0 -
b0 ,
bx +
b0 *
bx )
b0 (
b0 '
0&
b0 %
b0 $
bx #
0"
0!
$end
#2
b0 #
b0 )
b0 +
1"
1&
#4
0&
#6
b11 *
b10 $
b10 '
b10 -
b11 %
b11 (
b11 ,
1&
#8
0&
#10
b11 #
b11 )
b11 +
b0 *
b0 $
b0 '
b0 -
b1 %
b1 (
b1 ,
1!
1&
#12
0&
#14
b0 #
b0 )
b0 +
b10 *
b10 $
b10 '
b10 -
b0 %
b0 (
b0 ,
1&
#16
0&
#18
b10 #
b10 )
b10 +
b0 *
b1 $
b1 '
b1 -
0!
1&
#20
0&
#22
b0 #
b0 )
b0 +
b11 *
b10 $
b10 '
b10 -
b11 %
b11 (
b11 ,
1&
#24
0&
#26
b11 #
b11 )
b11 +
1&
