Tarea5/testbenchVerificador.v
module testbenchVerificador(

	output reg clk,
	output reg reset_L,
	output reg selector,
	output reg [1:0] data_in0,
	output reg [1:0] data_in1,
	input [1:0] data_outCond, data_outGenerico, data_outRetardos);

    reg [5:0] checkerGenerico, checkerRetardo;

	initial clk <= 0;     /*Inicialización del clock*/
    always #10 clk <= ~clk;

    initial 
    begin 
        $dumpfile("verificacion.vcd"); /*En este archivo se guardan todos los valores de la simulación*/
        $dumpvars;

        reset_L = 0;
        selector = 0;
        data_in0 = 0;
        data_in1 = 0;
        checkerGenerico = 0; checkerRetardo = 0;

        @(posedge clk);
        reset_L <= 1;

        @(posedge clk);
        data_in0 <= 3;
        data_in1 <= 2;

        @(posedge clk);
        selector <= 1;
        data_in0 <= 1;
        data_in1 <= 0;

        @(posedge clk);
        data_in0 <= 0;
        data_in1 <= 2;

        @(posedge clk);
        selector <= 0;
        data_in0 <= 0;
        data_in1 <= 1;

        @(posedge clk);
        data_in0 <= 3;
        data_in1 <= 2;

        #50 $finish;
    end

//Checker modelo generico
always @(posedge clk ) 
begin
    if (data_outCond != data_outGenerico) checkerGenerico <= checkerGenerico+1;
    else checkerGenerico <= checkerGenerico+0; 
end

//Checker modelo con retardos
always @(posedge clk ) 
begin
    if (data_outCond != data_outRetardos) checkerRetardo <= checkerRetardo+1;
    else checkerRetardo <= checkerRetardo+0; 
end

endmodule

Tarea5/estructural2.v
/* Generated by Yosys 0.9 (git sha1 1979e0b) */

(* top =  1  *)
(* src = "muxmemoriaconductual.v:1" *)
module muxRetardos(clk, reset_L, selector, data_in0, data_in1, data_out);
  (* src = "muxmemoriaconductual.v:18" *)
  wire [1:0] _00_;
  wire _01_;
  wire _02_;
  wire _03_;
  wire _04_;
  wire _05_;
  wire _06_;
  wire _07_;
  wire _08_;
  (* src = "muxmemoriaconductual.v:3" *)
  input clk;
  (* src = "muxmemoriaconductual.v:6" *)
  input [1:0] data_in0;
  (* src = "muxmemoriaconductual.v:7" *)
  input [1:0] data_in1;
  (* src = "muxmemoriaconductual.v:8" *)
  output [1:0] data_out;
  (* src = "muxmemoriaconductual.v:4" *)
  input reset_L;
  (* src = "muxmemoriaconductual.v:5" *)
  input selector;
  NOT _09_ (
    .A(data_in1[0]),
    .Y(_08_)
  );
  NOT _10_ (
    .A(data_in1[1]),
    .Y(_01_)
  );
  NOR _11_ (
    .A(selector),
    .B(data_in0[1]),
    .Y(_02_)
  );
  NAND _12_ (
    .A(selector),
    .B(_01_),
    .Y(_03_)
  );
  NAND _13_ (
    .A(reset_L),
    .B(_03_),
    .Y(_04_)
  );
  NOR _14_ (
    .A(_02_),
    .B(_04_),
    .Y(_00_[1])
  );
  NOR _15_ (
    .A(data_in0[0]),
    .B(selector),
    .Y(_05_)
  );
  NAND _16_ (
    .A(_08_),
    .B(selector),
    .Y(_06_)
  );
  NAND _17_ (
    .A(reset_L),
    .B(_06_),
    .Y(_07_)
  );
  NOR _18_ (
    .A(_05_),
    .B(_07_),
    .Y(_00_[0])
  );
  (* src = "muxmemoriaconductual.v:18" *)
  DFF _19_ (
    .C(clk),
    .D(_00_[0]),
    .Q(data_out[0])
  );
  (* src = "muxmemoriaconductual.v:18" *)
  DFF _20_ (
    .C(clk),
    .D(_00_[1]),
    .Q(data_out[1])
  );
endmodule

Tarea5/estructural1.v
/* Generated by Yosys 0.9 (git sha1 1979e0b) */

(* top =  1  *)
(* src = "muxmemoriaconductual.v:1" *)
module muxGenerico(clk, reset_L, selector, data_in0, data_in1, data_out);
  (* src = "muxmemoriaconductual.v:18" *)
  wire [1:0] _0_;
  (* src = "muxmemoriaconductual.v:3" *)
  input clk;
  (* src = "muxmemoriaconductual.v:6" *)
  input [1:0] data_in0;
  (* src = "muxmemoriaconductual.v:7" *)
  input [1:0] data_in1;
  (* src = "muxmemoriaconductual.v:8" *)
  output [1:0] data_out;
  reg [1:0] data_out;
  (* src = "muxmemoriaconductual.v:10" *)
  wire [1:0] mout;
  (* src = "muxmemoriaconductual.v:4" *)
  input reset_L;
  (* src = "muxmemoriaconductual.v:5" *)
  input selector;
  assign _0_[0] = reset_L ? (* src = "muxmemoriaconductual.v:20" *) mout[0] : 1'h0;
  assign _0_[1] = reset_L ? (* src = "muxmemoriaconductual.v:20" *) mout[1] : 1'h0;
  assign mout[0] = selector ? (* src = "muxmemoriaconductual.v:14" *) data_in1[0] : data_in0[0];
  assign mout[1] = selector ? (* src = "muxmemoriaconductual.v:14" *) data_in1[1] : data_in0[1];
  (* src = "muxmemoriaconductual.v:18" *)
  always @(posedge clk)
      data_out[0] <= _0_[0];
  (* src = "muxmemoriaconductual.v:18" *)
  always @(posedge clk)
      data_out[1] <= _0_[1];
endmodule

Tarea 2/muxmemoriaconductual.v
module mux_mem_conductual(

	input clk,
	input reset_L,
	input selector,
	input [1:0] data_in0,
	input [1:0] data_in1,
	output reg [1:0] data_out);
	
	reg [1:0] mout;
	
	always @ (*)
	begin 
		if (~selector) mout = data_in0;
		else mout = data_in1;
	end
	
	always @ (posedge clk)
	begin
		if (~reset_L) data_out <= 0;
		else data_out <= mout;
	end
		
endmodule

Tarea5/probadorVerificador.v
`timescale 1ns/100ps
`include "muxmemoriaconductual.v"
`include "testbenchVerificador.v"
`include "cmos_cellsRetardos.v"
`include "estructural1.v"
`include "estructural2.v"

module probadorVerificador();

wire clk, reset_L, selector;
wire [1:0] data_in0, data_in1, data_outCond, data_outGenerico, data_outRetardos;

mux_mem_conductual muxCond (.clk(clk), .reset_L(reset_L), .selector(selector), .data_in0(data_in0), .data_in1(data_in1), .data_out(data_outCond));
muxGenerico muxGen (.clk(clk), .reset_L(reset_L), .selector(selector), .data_in0(data_in0), .data_in1(data_in1), .data_out(data_outGenerico));
muxRetardos muxRet (.clk(clk), .reset_L(reset_L), .selector(selector), .data_in0(data_in0), .data_in1(data_in1), .data_out(data_outRetardos));
testbenchVerificador pruebaModelos (.clk(clk), .reset_L(reset_L), .selector(selector), .data_in0(data_in0), .data_in1(data_in1), .data_outCond(data_outCond), .data_outGenerico(data_outGenerico), .data_outRetardos(data_outRetardos));
endmodule

Tarea5/cmos_cellsRetardos.v
module BUF(A, Y);
input A;
output Y;
assign #(1:2.4:3.5, 1:2.4:3.5) Y = A;
endmodule

module NOT(A, Y);
input A;
output Y;
assign #(0.7:2:3.3, 0.7:2:3.3) Y = ~A;
endmodule

module NAND(A, B, Y);
input A, B;
output Y;
assign #(1:2.4:3.5, 1:2.4:3.5) Y = ~(A & B);
endmodule

module NOR(A, B, Y);
input A, B;
output Y;
assign #(0.9:2.25:3.6, 0.9:2.25:3.6) Y = ~(A | B);
endmodule

module DFF(C, D, Q);
input C, D;
output reg Q;
always @(posedge C)
	Q <= D;
endmodule

module DFFSR(C, D, Q, S, R);
input C, D, S, R;
output reg Q;
always @(posedge C, posedge S, posedge R)
	if (S)
		Q <= 1'b1;
	else if (R)
		Q <= 1'b0;
	else
		Q <= D;
endmodule

Tarea5/verificacion.vcd
$date
	Sun Sep 19 00:24:44 2021
$end
$version
	Icarus Verilog
$end
$timescale
	100ps
$end
$scope module BUF $end
$var wire 1 ! A $end
$var wire 1 " Y $end
$upscope $end
$scope module DFFSR $end
$var wire 1 # C $end
$var wire 1 $ D $end
$var wire 1 % R $end
$var wire 1 & S $end
$var reg 1 ' Q $end
$upscope $end
$scope module probadorVerificador $end
$var wire 1 ( selector $end
$var wire 1 ) reset_L $end
$var wire 2 * data_outRetardos [1:0] $end
$var wire 2 + data_outGenerico [1:0] $end
$var wire 2 , data_outCond [1:0] $end
$var wire 2 - data_in1 [1:0] $end
$var wire 2 . data_in0 [1:0] $end
$var wire 1 / clk $end
$scope module muxCond $end
$var wire 1 ( selector $end
$var wire 1 ) reset_L $end
$var wire 2 0 data_in1 [1:0] $end
$var wire 2 1 data_in0 [1:0] $end
$var wire 1 / clk $end
$var reg 2 2 data_out [1:0] $end
$var reg 2 3 mout [1:0] $end
$upscope $end
$scope module muxGen $end
$var wire 1 ( selector $end
$var wire 1 ) reset_L $end
$var wire 2 4 mout [1:0] $end
$var wire 2 5 data_in1 [1:0] $end
$var wire 2 6 data_in0 [1:0] $end
$var wire 1 / clk $end
$var wire 2 7 _0_ [1:0] $end
$var reg 2 8 data_out [1:0] $end
$upscope $end
$scope module muxRet $end
$var wire 1 ( selector $end
$var wire 1 ) reset_L $end
$var wire 2 9 data_out [1:0] $end
$var wire 2 : data_in1 [1:0] $end
$var wire 2 ; data_in0 [1:0] $end
$var wire 1 / clk $end
$var wire 1 < _08_ $end
$var wire 1 = _07_ $end
$var wire 1 > _06_ $end
$var wire 1 ? _05_ $end
$var wire 1 @ _04_ $end
$var wire 1 A _03_ $end
$var wire 1 B _02_ $end
$var wire 1 C _01_ $end
$var wire 2 D _00_ [1:0] $end
$scope module _09_ $end
$var wire 1 E A $end
$var wire 1 < Y $end
$upscope $end
$scope module _10_ $end
$var wire 1 F A $end
$var wire 1 C Y $end
$upscope $end
$scope module _11_ $end
$var wire 1 G B $end
$var wire 1 B Y $end
$var wire 1 ( A $end
$upscope $end
$scope module _12_ $end
$var wire 1 C B $end
$var wire 1 A Y $end
$var wire 1 ( A $end
$upscope $end
$scope module _13_ $end
$var wire 1 A B $end
$var wire 1 @ Y $end
$var wire 1 ) A $end
$upscope $end
$scope module _14_ $end
$var wire 1 B A $end
$var wire 1 @ B $end
$var wire 1 H Y $end
$upscope $end
$scope module _15_ $end
$var wire 1 I A $end
$var wire 1 ? Y $end
$var wire 1 ( B $end
$upscope $end
$scope module _16_ $end
$var wire 1 < A $end
$var wire 1 > Y $end
$var wire 1 ( B $end
$upscope $end
$scope module _17_ $end
$var wire 1 > B $end
$var wire 1 = Y $end
$var wire 1 ) A $end
$upscope $end
$scope module _18_ $end
$var wire 1 ? A $end
$var wire 1 = B $end
$var wire 1 J Y $end
$upscope $end
$scope module _19_ $end
$var wire 1 K D $end
$var wire 1 / C $end
$var reg 1 L Q $end
$upscope $end
$scope module _20_ $end
$var wire 1 M D $end
$var wire 1 / C $end
$var reg 1 N Q $end
$upscope $end
$upscope $end
$scope module pruebaModelos $end
$var wire 2 O data_outCond [1:0] $end
$var wire 2 P data_outGenerico [1:0] $end
$var wire 2 Q data_outRetardos [1:0] $end
$var reg 6 R checkerGenerico [5:0] $end
$var reg 6 S checkerRetardo [5:0] $end
$var reg 1 / clk $end
$var reg 2 T data_in0 [1:0] $end
$var reg 2 U data_in1 [1:0] $end
$var reg 1 ) reset_L $end
$var reg 1 ( selector $end
$upscope $end
$upscope $end
$enddefinitions $end
#0
$dumpvars
b0 U
b0 T
b0 S
b0 R
bx Q
bx P
bx O
xN
xM
xL
xK
xJ
0I
xH
0G
0F
0E
bx D
xC
xB
xA
x@
x?
x>
x=
x<
b0 ;
b0 :
bx 9
bx 8
b0 7
b0 6
b0 5
b0 4
b0 3
bx 2
b0 1
b0 0
0/
b0 .
b0 -
bx ,
bx +
bx *
0)
0(
x'
z&
z%
z$
z#
x"
z!
$end
#20
1C
1<
#23
1?
1B
#24
1=
1>
1@
1A
z"
#46
0K
0M
0J
b0 D
0H
#100
b0 ,
b0 2
b0 O
b0 +
b0 8
b0 P
0L
b0 *
b0 9
b0 Q
0N
1)
1/
#124
0=
0@
#200
0/
#300
b11 7
b11 4
1F
1I
1G
b11 3
b10 -
b10 0
b10 5
b10 :
b10 U
b11 .
b11 1
b11 6
b11 ;
b11 T
1/
#320
0C
#323
0?
0B
#346
1K
1M
1J
b11 D
1H
#400
0/
#500
b0 7
0F
0G
b0 4
b0 3
b11 ,
b11 2
b11 O
b11 +
b11 8
b11 P
1L
b11 *
b11 9
b11 Q
1N
b0 -
b0 0
b0 5
b0 :
b0 U
b1 .
b1 1
b1 6
b1 ;
b1 T
1(
1/
#520
1C
#524
0>
#544
0A
#548
1=
#568
1@
#571
0K
b10 D
0J
#591
0M
b0 D
0H
#600
0/
#700
b10 7
b10 4
1F
0I
b10 3
b10 -
b10 0
b10 5
b10 :
b10 U
b0 .
b0 1
b0 6
b0 ;
b0 T
0N
b0 *
b0 9
b0 Q
0L
b0 +
b0 8
b0 P
b0 ,
b0 2
b0 O
1/
#720
0C
#744
1A
#768
0@
#791
1M
b10 D
1H
#800
0/
#900
b0 7
0F
1E
b0 4
b0 3
b10 ,
b10 2
b10 O
b10 +
b10 8
b10 P
b10 *
b10 9
b10 Q
1N
b1 -
b1 0
b1 5
b1 :
b1 U
0(
1/
#920
1C
0<
#923
1?
1B
#924
1>
#946
0M
b0 D
0H
#948
0=
#1000
0/
#1100
b11 7
b11 4
1F
0E
1I
1G
b11 3
b10 -
b10 0
b10 5
b10 :
b10 U
b11 .
b11 1
b11 6
b11 ;
b11 T
b0 *
b0 9
b0 Q
0N
b0 +
b0 8
b0 P
b0 ,
b0 2
b0 O
1/
#1120
0C
1<
#1123
0?
0B
#1146
1K
1M
1J
b11 D
1H
#1200
0/
#1300
b11 ,
b11 2
b11 O
b11 +
b11 8
b11 P
1L
b11 *
b11 9
b11 Q
1N
1/
